headerexposer/__init__.py
headerexposer/__main__.py
headerexposer/baseline.json
headerexposer/baseline_schema.json
headerexposer/baseline_short.json
headerexposer-0.8a15.dist-info/LICENSE.txt
headerexposer-0.8a15.dist-info/METADATA
headerexposer-0.8a15.dist-info/WHEEL
headerexposer-0.8a15.dist-info/entry_points.txt
headerexposer-0.8a15.dist-info/top_level.txt
headerexposer-0.8a15.dist-info/RECORD
