Metadata-Version: 2.1
Name: headerexposer
Version: 0.8a15
Summary: Analyse the security of your website's headers!
Home-page: https://github.com/LivinParadoX/headerexposer
Author: Alexandre Janvrin
Author-email: alexandre.janvrin@reseau.eseo.fr
License: UNKNOWN
Keywords: http headers security analysis owasp recommendations best practices
Platform: UNKNOWN
Classifier: Development Status :: 3 - Alpha
Classifier: Intended Audience :: Information Technology
Classifier: Programming Language :: Python :: 3.7
Classifier: Programming Language :: Python :: 3.8
Classifier: Programming Language :: Python :: 3.9
Classifier: License :: OSI Approved :: GNU Affero General Public License v3 or later (AGPLv3+)
Classifier: Natural Language :: English
Classifier: Operating System :: OS Independent
Classifier: Topic :: Education :: Testing
Classifier: Topic :: Internet :: WWW/HTTP
Classifier: Topic :: Security
Requires-Python: >=3.7
Requires-Dist: ansiwrap
Requires-Dist: colorama
Requires-Dist: jsonschema
Requires-Dist: requests
Requires-Dist: tabulate
Requires-Dist: urllib3
